ring_seq/RingSeq.py
ring_seq/__init__.py
ring_seq/methods.py
ring_seq/examples/Ring.py
ring_seq/examples/__init__.py
ring_seq_py-1.0.dist-info/LICENSE
ring_seq_py-1.0.dist-info/METADATA
ring_seq_py-1.0.dist-info/WHEEL
ring_seq_py-1.0.dist-info/top_level.txt
ring_seq_py-1.0.dist-info/RECORD
