Metadata-Version: 2.1
Name: ring-seq-py
Version: 1.0
Summary: Extends list, tuple and str with ring (circular) methods
Author-email: Mario Càllisto <mario.callisto@gmail.com>
Project-URL: Homepage, https://scala-tessella.github.io/ring-seq-py/
Project-URL: Issues, https://github.com/scala-tessella/ring-seq-py/issues
Classifier: Intended Audience :: Developers
Classifier: License :: OSI Approved :: Apache Software License
Classifier: Programming Language :: Python :: 3
Classifier: Operating System :: OS Independent
Requires-Python: >=3.10
License-File: LICENSE
